fracas/__init__.py
fracas/__main__.py
fracas/config.py
fracas/crypto.py
fracas/dialog.py
fracas/io.py
fracas/journal.py
fracas-1.0.0.dist-info/LICENSE
fracas-1.0.0.dist-info/METADATA
fracas-1.0.0.dist-info/WHEEL
fracas-1.0.0.dist-info/entry_points.txt
fracas-1.0.0.dist-info/top_level.txt
fracas-1.0.0.dist-info/RECORD
