Metadata-Version: 2.1
Name: fracas
Version: 1.0.0
Summary: Command-line journal
Author-email: Craig Howard <craig@seagrape.us>
Project-URL: Homepage, https://seagrape.us/fracas.html
Project-URL: Repository, https://pypi.org/project/fracas/
Project-URL: Changelog, https://seagrape.us/fracas-history.html
Classifier: Programming Language :: Python :: 3
Classifier: License :: OSI Approved :: MIT License
Classifier: Operating System :: OS Independent
License-File: LICENSE
